talp_pages/__init__.py
talp_pages/analysis/__init__.py
talp_pages/analysis/badge_analysis.py
talp_pages/analysis/scaling_analysis.py
talp_pages/analysis/time_series_analysis.py
talp_pages/cli/ci_report.py
talp_pages/cli/download_github.py
talp_pages/cli/download_gitlab.py
talp_pages/cli/metadata.py
talp_pages/common.py
talp_pages/html/__init__.py
talp_pages/html/ci_report_index_page.py
talp_pages/html/scaling_result_site.py
talp_pages/html/site.py
talp_pages/html/templates/base.html.jinja
talp_pages/html/templates/index.jinja
talp_pages/html/templates/scaling.jinja
talp_pages/html/templates/time_series.jinja
talp_pages/html/time_series_result_site.py
talp_pages/io/__init__.py
talp_pages/io/dataframe_handling.py
talp_pages/io/output.py
talp_pages/io/run_folders.py
talp_pages/plots/__init__.py
talp_pages/plots/scaling_table_html_plot.py
talp_pages/plots/time_series_html_plot.py
talp_pages/reports/__init__.py
talp_pages/reports/ci_report.py
talp_pages/svg/__init__.py
talp_pages/svg/badge.py
talp_pages/talp.py
talp_pages-3.5.2.dist-info/METADATA
talp_pages-3.5.2.dist-info/WHEEL
talp_pages-3.5.2.dist-info/entry_points.txt
talp_pages-3.5.2.dist-info/RECORD
