Metadata-Version: 2.3
Name: talp-pages
Version: 3.5.2
Summary: Command line tools to generate performance reports using the TALP module of DLB
License: GPL-3.0-only
Keywords: HPC,Performance Analysis,Profiling,Continuous Performance Analysis
Author: Valentin Seitz
Author-email: valentin.seitz@bsc.es
Maintainer: Valentin Seitz
Maintainer-email: valentin.seitz@bsc.es
Requires-Python: >=3.9,<4.0
Classifier: Intended Audience :: Science/Research
Classifier: License :: OSI Approved :: GNU General Public License v3 (GPLv3)
Classifier: Operating System :: OS Independent
Classifier: Programming Language :: Python :: 3
Classifier: Programming Language :: Python :: 3.9
Classifier: Programming Language :: Python :: 3.10
Classifier: Programming Language :: Python :: 3.11
Classifier: Programming Language :: Python :: 3.12
Classifier: Programming Language :: Python :: 3.13
Classifier: Topic :: Scientific/Engineering :: Visualization
Classifier: Topic :: System :: Distributed Computing
Requires-Dist: jinja2 (>=3.1.4,<4.0.0)
Requires-Dist: kaleido (==0.2.1)
Requires-Dist: pandas (>=2.2.2,<3.0.0)
Requires-Dist: plotly
Requires-Dist: python-gitlab (>=4.4.0,<5.0.0)
Requires-Dist: tqdm
Project-URL: Homepage, https://pm.bsc.es/gitlab/dlb/dlb/
Project-URL: Repository, https://pm.bsc.es/gitlab/dlb/dlb/
